django_pagination_fork-1.0.17.dist-info/DESCRIPTION.rst
django_pagination_fork-1.0.17.dist-info/METADATA
django_pagination_fork-1.0.17.dist-info/RECORD
django_pagination_fork-1.0.17.dist-info/WHEEL
django_pagination_fork-1.0.17.dist-info/metadata.json
django_pagination_fork-1.0.17.dist-info/top_level.txt
pagination/__init__.py
pagination/middleware.py
pagination/models.py
pagination/paginator.py
pagination/tests.py
pagination/templates/pagination/pagination.html
pagination/templatetags/__init__.py
pagination/templatetags/pagination_tags.py
